tests/anova_tests.py
tests/kruskalwallis_tests.py
tests/probability_tests.py
tests/regress_visual_test.py
tests/statistics_tests.py
tests/std_tests.py
tests/utils_tests.py
tests/visualization_tests.py
statstoolkit-1.0.4.dist-info/LICENSE
statstoolkit-1.0.4.dist-info/METADATA
statstoolkit-1.0.4.dist-info/WHEEL
statstoolkit-1.0.4.dist-info/top_level.txt
statstoolkit-1.0.4.dist-info/RECORD
