Metadata-Version: 2.2
Name: statstoolkit
Version: 1.0.4
Summary: Statistical Methods for Data Science Toolkit
Author: Eng. Marco Schivo and Eng. Alberto Biscalchin
Author-email: "Eng. Marco Schivo" <marcoschivo1@gmail.com>, "Eng. Alberto Biscalchin" <biscalchin.mau.se@gmail.com>
License: MIT License
Keywords: statistics,data science,machine learning,data analysis,descriptive statistics,probability distributions,visualizations
Classifier: Development Status :: 5 - Production/Stable
Classifier: Intended Audience :: Developers
Classifier: Intended Audience :: Science/Research
Classifier: Programming Language :: Python :: 3
Classifier: Operating System :: OS Independent
Classifier: License :: OSI Approved :: MIT License
License-File: LICENSE
Requires-Dist: numpy
Requires-Dist: scipy
Requires-Dist: pandas
Requires-Dist: matplotlib
Requires-Dist: seaborn
Requires-Dist: statsmodels
Requires-Dist: pingouin
Dynamic: author
